langchain_google_cloud_sql_pg/__init__.py
langchain_google_cloud_sql_pg/async_chat_message_history.py
langchain_google_cloud_sql_pg/async_checkpoint.py
langchain_google_cloud_sql_pg/async_loader.py
langchain_google_cloud_sql_pg/async_vectorstore.py
langchain_google_cloud_sql_pg/chat_message_history.py
langchain_google_cloud_sql_pg/checkpoint.py
langchain_google_cloud_sql_pg/engine.py
langchain_google_cloud_sql_pg/indexes.py
langchain_google_cloud_sql_pg/loader.py
langchain_google_cloud_sql_pg/py.typed
langchain_google_cloud_sql_pg/vectorstore.py
langchain_google_cloud_sql_pg/version.py
langchain_google_cloud_sql_pg-0.14.1.dist-info/licenses/LICENSE
langchain_google_cloud_sql_pg-0.14.1.dist-info/METADATA
langchain_google_cloud_sql_pg-0.14.1.dist-info/WHEEL
langchain_google_cloud_sql_pg-0.14.1.dist-info/top_level.txt
langchain_google_cloud_sql_pg-0.14.1.dist-info/RECORD
